{
  "Instance": "Instance7_2_1",
  "Objective": 782,
  "NumberOfAllTasks": 277,
  "UseMainTasks": true,
  "Days": {
    "1": [
      {
        "CohortID": 0,
        "Profit": 68,
        "Route": [
          {
            "StartTime": 290,
            "SelectedDay": 1,
            "ID": "PE-FWI-4-8273"
          },
          {
            "StartTime": 992,
            "SelectedDay": 1,
            "ID": "PE-FWI-4-6119"
          },
          {
            "StartTime": 1819,
            "SelectedDay": 1,
            "ID": "PE-FWI-4-7458"
          },
          {
            "StartTime": 2550,
            "SelectedDay": 1,
            "ID": "PE-FWI-1-7228"
          },
          {
            "StartTime": 3291,
            "SelectedDay": 1,
            "ID": "PE-FWI-4-8877"
          },
          {
            "StartTime": 4168,
            "SelectedDay": 1,
            "ID": "PE-FWI-4-6688"
          },
          {
            "StartTime": 4784,
            "SelectedDay": 1,
            "ID": "PE-FWI-2-285"
          },
          {
            "StartTime": 5400,
            "SelectedDay": 1,
            "ID": "MT-FWI-2"
          },
          {
            "StartTime": 10003,
            "SelectedDay": 1,
            "ID": "PE-FWI-4-1976"
          },
          {
            "StartTime": 10727,
            "SelectedDay": 1,
            "ID": "PE-FWI-4-3987"
          },
          {
            "StartTime": 11340,
            "SelectedDay": 1,
            "ID": "PE-FWI-4-5359"
          },
          {
            "StartTime": 12163,
            "SelectedDay": 1,
            "ID": "PE-FWI-4-3054"
          },
          {
            "StartTime": 12967,
            "SelectedDay": 1,
            "ID": "PE-FWI-4-5530"
          },
          {
            "StartTime": 13578,
            "SelectedDay": 1,
            "ID": "PE-FWI-4-7153"
          },
          {
            "StartTime": 14198,
            "SelectedDay": 1,
            "ID": "PE-FWI-4-2043"
          },
          {
            "StartTime": 14892,
            "SelectedDay": 1,
            "ID": "PE-FWI-4-112"
          },
          {
            "StartTime": 15557,
            "SelectedDay": 1,
            "ID": "PE-FWI-4-8705"
          },
          {
            "StartTime": 16412,
            "SelectedDay": 1,
            "ID": "PE-FWI-4-1056"
          },
          {
            "StartTime": 17083,
            "SelectedDay": 1,
            "ID": "PE-FWI-4-5635"
          },
          {
            "StartTime": 17718,
            "SelectedDay": 1,
            "ID": "PE-FWI-4-1714"
          },
          {
            "StartTime": 18422,
            "SelectedDay": 1,
            "ID": "PE-FWI-4-3387"
          },
          {
            "StartTime": 19070,
            "SelectedDay": 1,
            "ID": "PE-FWI-4-8196"
          },
          {
            "StartTime": 19823,
            "SelectedDay": 1,
            "ID": "PE-FWI-4-5639"
          },
          {
            "StartTime": 20514,
            "SelectedDay": 1,
            "ID": "PE-FWI-4-9106"
          }
        ]
      },
      {
        "CohortID": 1,
        "Profit": 54,
        "Route": [
          {
            "StartTime": 602,
            "SelectedDay": 1,
            "ID": "PE-FWI-4-2325"
          },
          {
            "StartTime": 1709,
            "SelectedDay": 1,
            "ID": "PE-FWI-4-6077"
          },
          {
            "StartTime": 2539,
            "SelectedDay": 1,
            "ID": "PE-FWI-4-4328"
          },
          {
            "StartTime": 3199,
            "SelectedDay": 1,
            "ID": "PE-FWI-4-3260"
          },
          {
            "StartTime": 4099,
            "SelectedDay": 1,
            "ID": "PE-FWI-4-1923"
          },
          {
            "StartTime": 4908,
            "SelectedDay": 1,
            "ID": "PE-FWI-4-3474"
          },
          {
            "StartTime": 5578,
            "SelectedDay": 1,
            "ID": "PE-FWI-4-2864"
          },
          {
            "StartTime": 6274,
            "SelectedDay": 1,
            "ID": "PE-FWI-4-7794"
          },
          {
            "StartTime": 7138,
            "SelectedDay": 1,
            "ID": "PE-FWI-4-728"
          },
          {
            "StartTime": 7754,
            "SelectedDay": 1,
            "ID": "PE-FWI-4-3577"
          },
          {
            "StartTime": 8577,
            "SelectedDay": 1,
            "ID": "PE-FWI-4-5005"
          },
          {
            "StartTime": 9491,
            "SelectedDay": 1,
            "ID": "PE-FWI-4-6503"
          },
          {
            "StartTime": 10182,
            "SelectedDay": 1,
            "ID": "PE-FWI-4-917"
          },
          {
            "StartTime": 10819,
            "SelectedDay": 1,
            "ID": "PE-FWI-4-4682"
          },
          {
            "StartTime": 11700,
            "SelectedDay": 1,
            "ID": "MT-FWI-3"
          },
          {
            "StartTime": 17222,
            "SelectedDay": 1,
            "ID": "PE-FWI-4-6887"
          },
          {
            "StartTime": 18458,
            "SelectedDay": 1,
            "ID": "PE-FWI-1-1655"
          },
          {
            "StartTime": 19290,
            "SelectedDay": 1,
            "ID": "PE-FWI-4-8595"
          },
          {
            "StartTime": 20137,
            "SelectedDay": 1,
            "ID": "PE-FWI-4-2184"
          }
        ]
      },
      {
        "CohortID": 2,
        "Profit": 51,
        "Route": [
          {
            "StartTime": 1180,
            "SelectedDay": 1,
            "ID": "PE-FWI-4-1087"
          },
          {
            "StartTime": 2085,
            "SelectedDay": 1,
            "ID": "PE-FWI-4-1343"
          },
          {
            "StartTime": 2740,
            "SelectedDay": 1,
            "ID": "PE-FWI-4-1199"
          },
          {
            "StartTime": 3600,
            "SelectedDay": 1,
            "ID": "MT-FWI-6"
          },
          {
            "StartTime": 9900,
            "SelectedDay": 1,
            "ID": "PE-FWI-4-3304"
          },
          {
            "StartTime": 10565,
            "SelectedDay": 1,
            "ID": "PE-FWI-4-950"
          },
          {
            "StartTime": 11219,
            "SelectedDay": 1,
            "ID": "PE-FWI-4-3"
          },
          {
            "StartTime": 11887,
            "SelectedDay": 1,
            "ID": "PE-FWI-4-9637"
          },
          {
            "StartTime": 12674,
            "SelectedDay": 1,
            "ID": "PE-FWI-4-6422"
          },
          {
            "StartTime": 13430,
            "SelectedDay": 1,
            "ID": "PE-FWI-1-699"
          },
          {
            "StartTime": 14256,
            "SelectedDay": 1,
            "ID": "PE-FWI-4-2236"
          },
          {
            "StartTime": 14978,
            "SelectedDay": 1,
            "ID": "PE-FWI-4-9102"
          },
          {
            "StartTime": 15874,
            "SelectedDay": 1,
            "ID": "PE-FWI-4-3709"
          },
          {
            "StartTime": 16609,
            "SelectedDay": 1,
            "ID": "PE-FWI-4-5395"
          },
          {
            "StartTime": 17485,
            "SelectedDay": 1,
            "ID": "PE-FWI-4-4558"
          },
          {
            "StartTime": 18462,
            "SelectedDay": 1,
            "ID": "PE-FWI-4-5934"
          },
          {
            "StartTime": 19126,
            "SelectedDay": 1,
            "ID": "PE-FWI-4-149"
          },
          {
            "StartTime": 19990,
            "SelectedDay": 1,
            "ID": "PE-FWI-4-8811"
          }
        ]
      },
      {
        "CohortID": 3,
        "Profit": 57,
        "Route": [
          {
            "StartTime": 275,
            "SelectedDay": 1,
            "ID": "PE-FWI-4-7628"
          },
          {
            "StartTime": 1022,
            "SelectedDay": 1,
            "ID": "PE-FWI-4-5280"
          },
          {
            "StartTime": 1802,
            "SelectedDay": 1,
            "ID": "PE-FWI-4-8203"
          },
          {
            "StartTime": 2648,
            "SelectedDay": 1,
            "ID": "PE-FWI-4-8217"
          },
          {
            "StartTime": 3498,
            "SelectedDay": 1,
            "ID": "PE-FWI-4-1246"
          },
          {
            "StartTime": 4425,
            "SelectedDay": 1,
            "ID": "PE-FWI-4-1459"
          },
          {
            "StartTime": 5199,
            "SelectedDay": 1,
            "ID": "PE-FWI-4-4923"
          },
          {
            "StartTime": 5859,
            "SelectedDay": 1,
            "ID": "PE-FWI-4-8823"
          },
          {
            "StartTime": 6528,
            "SelectedDay": 1,
            "ID": "PE-FWI-1-2177"
          },
          {
            "StartTime": 7414,
            "SelectedDay": 1,
            "ID": "PE-FWI-4-2246"
          },
          {
            "StartTime": 8100,
            "SelectedDay": 1,
            "ID": "MT-FWI-7"
          },
          {
            "StartTime": 13634,
            "SelectedDay": 1,
            "ID": "PE-FWI-1-6626"
          },
          {
            "StartTime": 14487,
            "SelectedDay": 1,
            "ID": "PE-FWI-4-5678"
          },
          {
            "StartTime": 15227,
            "SelectedDay": 1,
            "ID": "PE-FWI-4-518"
          },
          {
            "StartTime": 16070,
            "SelectedDay": 1,
            "ID": "PE-FWI-1-9165"
          },
          {
            "StartTime": 16867,
            "SelectedDay": 1,
            "ID": "PE-FWI-4-5155"
          },
          {
            "StartTime": 17670,
            "SelectedDay": 1,
            "ID": "PE-FWI-4-9377"
          },
          {
            "StartTime": 18439,
            "SelectedDay": 1,
            "ID": "PE-FWI-4-3501"
          },
          {
            "StartTime": 19330,
            "SelectedDay": 1,
            "ID": "PE-FWI-4-5284"
          },
          {
            "StartTime": 20344,
            "SelectedDay": 1,
            "ID": "PE-FWI-4-2749"
          }
        ]
      },
      {
        "CohortID": 4,
        "Profit": 63,
        "Route": [
          {
            "StartTime": 249,
            "SelectedDay": 1,
            "ID": "PE-FWI-4-8394"
          },
          {
            "StartTime": 945,
            "SelectedDay": 1,
            "ID": "PE-FWI-4-3601"
          },
          {
            "StartTime": 1658,
            "SelectedDay": 1,
            "ID": "PE-FWI-4-4043"
          },
          {
            "StartTime": 2389,
            "SelectedDay": 1,
            "ID": "PE-FWI-4-5845"
          },
          {
            "StartTime": 3294,
            "SelectedDay": 1,
            "ID": "PE-FWI-4-7361"
          },
          {
            "StartTime": 3914,
            "SelectedDay": 1,
            "ID": "PE-FWI-4-7174"
          },
          {
            "StartTime": 4653,
            "SelectedDay": 1,
            "ID": "PE-FWI-4-8574"
          },
          {
            "StartTime": 5331,
            "SelectedDay": 1,
            "ID": "PE-FWI-4-2791"
          },
          {
            "StartTime": 6094,
            "SelectedDay": 1,
            "ID": "PE-FWI-4-6408"
          },
          {
            "StartTime": 7200,
            "SelectedDay": 1,
            "ID": "MT-FWI-9"
          },
          {
            "StartTime": 11762,
            "SelectedDay": 1,
            "ID": "PE-FWI-4-7567"
          },
          {
            "StartTime": 12540,
            "SelectedDay": 1,
            "ID": "PE-FWI-4-5183"
          },
          {
            "StartTime": 13743,
            "SelectedDay": 1,
            "ID": "PE-FWI-4-9312"
          },
          {
            "StartTime": 14471,
            "SelectedDay": 1,
            "ID": "PE-FWI-4-8715"
          },
          {
            "StartTime": 15262,
            "SelectedDay": 1,
            "ID": "PE-FWI-4-8991"
          },
          {
            "StartTime": 15922,
            "SelectedDay": 1,
            "ID": "PE-FWI-1-6359"
          },
          {
            "StartTime": 16819,
            "SelectedDay": 1,
            "ID": "PE-FWI-4-1337"
          },
          {
            "StartTime": 17511,
            "SelectedDay": 1,
            "ID": "PE-FWI-4-304"
          },
          {
            "StartTime": 18231,
            "SelectedDay": 1,
            "ID": "PE-FWI-4-2563"
          },
          {
            "StartTime": 18917,
            "SelectedDay": 1,
            "ID": "PE-FWI-4-7527"
          },
          {
            "StartTime": 19596,
            "SelectedDay": 1,
            "ID": "PE-FWI-4-9605"
          },
          {
            "StartTime": 20354,
            "SelectedDay": 1,
            "ID": "PE-FWI-4-3617"
          }
        ]
      },
      {
        "CohortID": 5,
        "Profit": 48,
        "Route": [
          {
            "StartTime": 1558,
            "SelectedDay": 1,
            "ID": "PE-FWI-4-4821"
          },
          {
            "StartTime": 2582,
            "SelectedDay": 1,
            "ID": "PE-FWI-4-4523"
          },
          {
            "StartTime": 3421,
            "SelectedDay": 1,
            "ID": "PE-FWI-4-1402"
          },
          {
            "StartTime": 4157,
            "SelectedDay": 1,
            "ID": "PE-FWI-4-6045"
          },
          {
            "StartTime": 5075,
            "SelectedDay": 1,
            "ID": "PE-FWI-4-2231"
          },
          {
            "StartTime": 5738,
            "SelectedDay": 1,
            "ID": "PE-FWI-4-5124"
          },
          {
            "StartTime": 6371,
            "SelectedDay": 1,
            "ID": "PE-FWI-1-102"
          },
          {
            "StartTime": 7071,
            "SelectedDay": 1,
            "ID": "PE-FWI-4-5076"
          },
          {
            "StartTime": 7917,
            "SelectedDay": 1,
            "ID": "PE-FWI-4-3134"
          },
          {
            "StartTime": 9000,
            "SelectedDay": 1,
            "ID": "MT-FWI-10"
          },
          {
            "StartTime": 14457,
            "SelectedDay": 1,
            "ID": "PE-FWI-4-8078"
          },
          {
            "StartTime": 15375,
            "SelectedDay": 1,
            "ID": "PE-FWI-4-878"
          },
          {
            "StartTime": 16272,
            "SelectedDay": 1,
            "ID": "PE-FWI-4-4012"
          },
          {
            "StartTime": 17205,
            "SelectedDay": 1,
            "ID": "PE-FWI-4-1661"
          },
          {
            "StartTime": 17925,
            "SelectedDay": 1,
            "ID": "PE-FWI-4-383"
          },
          {
            "StartTime": 18627,
            "SelectedDay": 1,
            "ID": "PE-FWI-4-4434"
          },
          {
            "StartTime": 19567,
            "SelectedDay": 1,
            "ID": "PE-FWI-4-7650"
          }
        ]
      },
      {
        "CohortID": 6,
        "Profit": 54,
        "Route": [
          {
            "StartTime": 907,
            "SelectedDay": 1,
            "ID": "PE-FWI-4-5995"
          },
          {
            "StartTime": 1767,
            "SelectedDay": 1,
            "ID": "PE-FWI-4-5040"
          },
          {
            "StartTime": 2620,
            "SelectedDay": 1,
            "ID": "PE-FWI-4-8256"
          },
          {
            "StartTime": 3236,
            "SelectedDay": 1,
            "ID": "PE-FWI-4-6255"
          },
          {
            "StartTime": 3876,
            "SelectedDay": 1,
            "ID": "PE-FWI-4-828"
          },
          {
            "StartTime": 4731,
            "SelectedDay": 1,
            "ID": "PE-FWI-4-4146"
          },
          {
            "StartTime": 5428,
            "SelectedDay": 1,
            "ID": "PE-FWI-4-3445"
          },
          {
            "StartTime": 6552,
            "SelectedDay": 1,
            "ID": "PE-FWI-4-7501"
          },
          {
            "StartTime": 7277,
            "SelectedDay": 1,
            "ID": "PE-FWI-4-6409"
          },
          {
            "StartTime": 8100,
            "SelectedDay": 1,
            "ID": "MT-FWI-12"
          },
          {
            "StartTime": 13528,
            "SelectedDay": 1,
            "ID": "PE-FWI-4-4642"
          },
          {
            "StartTime": 14392,
            "SelectedDay": 1,
            "ID": "PE-FWI-4-152"
          },
          {
            "StartTime": 15231,
            "SelectedDay": 1,
            "ID": "PE-FWI-4-7930"
          },
          {
            "StartTime": 15896,
            "SelectedDay": 1,
            "ID": "PE-FWI-4-6891"
          },
          {
            "StartTime": 16546,
            "SelectedDay": 1,
            "ID": "PE-FWI-4-5331"
          },
          {
            "StartTime": 17278,
            "SelectedDay": 1,
            "ID": "PE-FWI-1-5341"
          },
          {
            "StartTime": 17938,
            "SelectedDay": 1,
            "ID": "PE-FWI-4-8625"
          },
          {
            "StartTime": 18951,
            "SelectedDay": 1,
            "ID": "PE-FWI-4-6846"
          },
          {
            "StartTime": 19700,
            "SelectedDay": 1,
            "ID": "PE-FWI-4-2200"
          }
        ]
      }
    ],
    "2": [
      {
        "CohortID": 0,
        "Profit": 54,
        "Route": [
          {
            "StartTime": 579,
            "SelectedDay": 2,
            "ID": "PE-FWI-4-7953"
          },
          {
            "StartTime": 1282,
            "SelectedDay": 2,
            "ID": "PE-FWI-4-2069"
          },
          {
            "StartTime": 2109,
            "SelectedDay": 2,
            "ID": "PE-FWI-1-8367"
          },
          {
            "StartTime": 2954,
            "SelectedDay": 2,
            "ID": "PE-FWI-1-2998"
          },
          {
            "StartTime": 3822,
            "SelectedDay": 2,
            "ID": "PE-FWI-4-9414"
          },
          {
            "StartTime": 4642,
            "SelectedDay": 2,
            "ID": "PE-FWI-4-9702"
          },
          {
            "StartTime": 5259,
            "SelectedDay": 2,
            "ID": "PE-FWI-4-8066"
          },
          {
            "StartTime": 5944,
            "SelectedDay": 2,
            "ID": "PE-FWI-4-1826"
          },
          {
            "StartTime": 6587,
            "SelectedDay": 2,
            "ID": "PE-FWI-4-2798"
          },
          {
            "StartTime": 7306,
            "SelectedDay": 2,
            "ID": "PE-FWI-4-357"
          },
          {
            "StartTime": 8114,
            "SelectedDay": 2,
            "ID": "PE-FWI-4-5115"
          },
          {
            "StartTime": 9000,
            "SelectedDay": 2,
            "ID": "MT-FWI-1"
          },
          {
            "StartTime": 15449,
            "SelectedDay": 2,
            "ID": "PE-FWI-4-7163"
          },
          {
            "StartTime": 16293,
            "SelectedDay": 2,
            "ID": "PE-FWI-4-6938"
          },
          {
            "StartTime": 17151,
            "SelectedDay": 2,
            "ID": "PE-FWI-4-4000"
          },
          {
            "StartTime": 17846,
            "SelectedDay": 2,
            "ID": "PE-FWI-1-9532"
          },
          {
            "StartTime": 18806,
            "SelectedDay": 2,
            "ID": "PE-FWI-4-7799"
          },
          {
            "StartTime": 19507,
            "SelectedDay": 2,
            "ID": "PE-FWI-4-8192"
          },
          {
            "StartTime": 20470,
            "SelectedDay": 2,
            "ID": "PE-FWI-4-3600"
          }
        ]
      },
      {
        "CohortID": 1,
        "Profit": 51,
        "Route": [
          {
            "StartTime": 750,
            "SelectedDay": 2,
            "ID": "PE-FWI-4-5377"
          },
          {
            "StartTime": 1551,
            "SelectedDay": 2,
            "ID": "PE-FWI-4-7444"
          },
          {
            "StartTime": 2194,
            "SelectedDay": 2,
            "ID": "PE-FWI-4-2913"
          },
          {
            "StartTime": 3314,
            "SelectedDay": 2,
            "ID": "PE-FWI-4-1006"
          },
          {
            "StartTime": 4146,
            "SelectedDay": 2,
            "ID": "PE-FWI-4-3796"
          },
          {
            "StartTime": 4807,
            "SelectedDay": 2,
            "ID": "PE-FWI-4-3015"
          },
          {
            "StartTime": 5487,
            "SelectedDay": 2,
            "ID": "PE-FWI-4-6888"
          },
          {
            "StartTime": 6479,
            "SelectedDay": 2,
            "ID": "PE-FWI-4-6465"
          },
          {
            "StartTime": 7200,
            "SelectedDay": 2,
            "ID": "MT-FWI-4"
          },
          {
            "StartTime": 13727,
            "SelectedDay": 2,
            "ID": "PE-FWI-4-2493"
          },
          {
            "StartTime": 14465,
            "SelectedDay": 2,
            "ID": "PE-FWI-4-8040"
          },
          {
            "StartTime": 15100,
            "SelectedDay": 2,
            "ID": "PE-FWI-4-147"
          },
          {
            "StartTime": 15844,
            "SelectedDay": 2,
            "ID": "PE-FWI-1-1683"
          },
          {
            "StartTime": 16652,
            "SelectedDay": 2,
            "ID": "PE-FWI-4-4269"
          },
          {
            "StartTime": 17530,
            "SelectedDay": 2,
            "ID": "PE-FWI-1-3135"
          },
          {
            "StartTime": 18162,
            "SelectedDay": 2,
            "ID": "PE-FWI-4-5276"
          },
          {
            "StartTime": 18936,
            "SelectedDay": 2,
            "ID": "PE-FWI-4-4339"
          },
          {
            "StartTime": 20201,
            "SelectedDay": 2,
            "ID": "PE-FWI-4-7372"
          }
        ]
      },
      {
        "CohortID": 2,
        "Profit": 60,
        "Route": [
          {
            "StartTime": 186,
            "SelectedDay": 2,
            "ID": "PE-FWI-4-5302"
          },
          {
            "StartTime": 891,
            "SelectedDay": 2,
            "ID": "PE-FWI-1-7220"
          },
          {
            "StartTime": 1697,
            "SelectedDay": 2,
            "ID": "PE-FWI-1-1776"
          },
          {
            "StartTime": 2974,
            "SelectedDay": 2,
            "ID": "PE-FWI-4-3330"
          },
          {
            "StartTime": 3663,
            "SelectedDay": 2,
            "ID": "PE-FWI-4-5274"
          },
          {
            "StartTime": 4600,
            "SelectedDay": 2,
            "ID": "PE-FWI-4-8463"
          },
          {
            "StartTime": 5400,
            "SelectedDay": 2,
            "ID": "MT-FWI-5"
          },
          {
            "StartTime": 10863,
            "SelectedDay": 2,
            "ID": "PE-FWI-4-8630"
          },
          {
            "StartTime": 11499,
            "SelectedDay": 2,
            "ID": "PE-FWI-4-3421"
          },
          {
            "StartTime": 12229,
            "SelectedDay": 2,
            "ID": "PE-FWI-4-3522"
          },
          {
            "StartTime": 12901,
            "SelectedDay": 2,
            "ID": "PE-FWI-1-487"
          },
          {
            "StartTime": 13597,
            "SelectedDay": 2,
            "ID": "PE-FWI-4-5261"
          },
          {
            "StartTime": 14216,
            "SelectedDay": 2,
            "ID": "PE-FWI-4-7599"
          },
          {
            "StartTime": 14996,
            "SelectedDay": 2,
            "ID": "PE-FWI-4-9685"
          },
          {
            "StartTime": 16016,
            "SelectedDay": 2,
            "ID": "PE-FWI-4-2002"
          },
          {
            "StartTime": 16856,
            "SelectedDay": 2,
            "ID": "PE-FWI-4-1989"
          },
          {
            "StartTime": 17556,
            "SelectedDay": 2,
            "ID": "PE-FWI-4-6177"
          },
          {
            "StartTime": 18376,
            "SelectedDay": 2,
            "ID": "PE-FWI-4-9927"
          },
          {
            "StartTime": 19163,
            "SelectedDay": 2,
            "ID": "PE-FWI-4-8855"
          },
          {
            "StartTime": 19986,
            "SelectedDay": 2,
            "ID": "PE-FWI-4-2712"
          },
          {
            "StartTime": 20666,
            "SelectedDay": 2,
            "ID": "PE-FWI-4-1453"
          },
          {
            "StartTime": 21591,
            "SelectedDay": 2,
            "ID": "PE-FWI-5-5985"
          }
        ]
      },
      {
        "CohortID": 3,
        "Profit": 63,
        "Route": [
          {
            "StartTime": 361,
            "SelectedDay": 2,
            "ID": "PE-FWI-4-7571"
          },
          {
            "StartTime": 1261,
            "SelectedDay": 2,
            "ID": "PE-FWI-1-5642"
          },
          {
            "StartTime": 2397,
            "SelectedDay": 2,
            "ID": "PE-FWI-4-1988"
          },
          {
            "StartTime": 3080,
            "SelectedDay": 2,
            "ID": "PE-FWI-4-2404"
          },
          {
            "StartTime": 4103,
            "SelectedDay": 2,
            "ID": "PE-FWI-4-2894"
          },
          {
            "StartTime": 4780,
            "SelectedDay": 2,
            "ID": "PE-FWI-4-3154"
          },
          {
            "StartTime": 5459,
            "SelectedDay": 2,
            "ID": "PE-FWI-4-6944"
          },
          {
            "StartTime": 6197,
            "SelectedDay": 2,
            "ID": "PE-FWI-4-9874"
          },
          {
            "StartTime": 6887,
            "SelectedDay": 2,
            "ID": "PE-FWI-4-7043"
          },
          {
            "StartTime": 7539,
            "SelectedDay": 2,
            "ID": "PE-FWI-4-4935"
          },
          {
            "StartTime": 8385,
            "SelectedDay": 2,
            "ID": "PE-FWI-4-9860"
          },
          {
            "StartTime": 9260,
            "SelectedDay": 2,
            "ID": "PE-FWI-4-6927"
          },
          {
            "StartTime": 10059,
            "SelectedDay": 2,
            "ID": "PE-FWI-4-2805"
          },
          {
            "StartTime": 10900,
            "SelectedDay": 2,
            "ID": "PE-FWI-4-7656"
          },
          {
            "StartTime": 11860,
            "SelectedDay": 2,
            "ID": "PE-FWI-4-7443"
          },
          {
            "StartTime": 12553,
            "SelectedDay": 2,
            "ID": "PE-FWI-1-2501"
          },
          {
            "StartTime": 13500,
            "SelectedDay": 2,
            "ID": "MT-FWI-8"
          },
          {
            "StartTime": 17256,
            "SelectedDay": 2,
            "ID": "PE-FWI-4-1889"
          },
          {
            "StartTime": 17955,
            "SelectedDay": 2,
            "ID": "PE-FWI-4-7839"
          },
          {
            "StartTime": 18761,
            "SelectedDay": 2,
            "ID": "PE-FWI-4-9325"
          },
          {
            "StartTime": 19479,
            "SelectedDay": 2,
            "ID": "PE-FWI-4-3288"
          },
          {
            "StartTime": 20422,
            "SelectedDay": 2,
            "ID": "PE-FWI-4-2254"
          }
        ]
      },
      {
        "CohortID": 4,
        "Profit": 60,
        "Route": [
          {
            "StartTime": 324,
            "SelectedDay": 2,
            "ID": "PE-FWI-4-5908"
          },
          {
            "StartTime": 1205,
            "SelectedDay": 2,
            "ID": "PE-FWI-4-1358"
          },
          {
            "StartTime": 2095,
            "SelectedDay": 2,
            "ID": "PE-FWI-4-9316"
          },
          {
            "StartTime": 3020,
            "SelectedDay": 2,
            "ID": "PE-FWI-4-9438"
          },
          {
            "StartTime": 3831,
            "SelectedDay": 2,
            "ID": "PE-FWI-4-5334"
          },
          {
            "StartTime": 4512,
            "SelectedDay": 2,
            "ID": "PE-FWI-4-7383"
          },
          {
            "StartTime": 5400,
            "SelectedDay": 2,
            "ID": "MT-FWI-11"
          },
          {
            "StartTime": 9962,
            "SelectedDay": 2,
            "ID": "PE-FWI-4-8170"
          },
          {
            "StartTime": 10823,
            "SelectedDay": 2,
            "ID": "PE-FWI-4-7661"
          },
          {
            "StartTime": 11699,
            "SelectedDay": 2,
            "ID": "PE-FWI-4-7920"
          },
          {
            "StartTime": 12435,
            "SelectedDay": 2,
            "ID": "PE-FWI-4-1213"
          },
          {
            "StartTime": 13271,
            "SelectedDay": 2,
            "ID": "PE-FWI-4-4862"
          },
          {
            "StartTime": 13980,
            "SelectedDay": 2,
            "ID": "PE-FWI-1-3755"
          },
          {
            "StartTime": 14654,
            "SelectedDay": 2,
            "ID": "PE-FWI-4-7028"
          },
          {
            "StartTime": 15290,
            "SelectedDay": 2,
            "ID": "PE-FWI-4-2852"
          },
          {
            "StartTime": 16147,
            "SelectedDay": 2,
            "ID": "PE-FWI-4-3559"
          },
          {
            "StartTime": 16975,
            "SelectedDay": 2,
            "ID": "PE-FWI-4-3953"
          },
          {
            "StartTime": 17709,
            "SelectedDay": 2,
            "ID": "PE-FWI-4-1611"
          },
          {
            "StartTime": 18450,
            "SelectedDay": 2,
            "ID": "PE-FWI-4-1769"
          },
          {
            "StartTime": 19393,
            "SelectedDay": 2,
            "ID": "PE-FWI-4-8828"
          },
          {
            "StartTime": 20038,
            "SelectedDay": 2,
            "ID": "PE-FWI-4-3315"
          }
        ]
      },
      {
        "CohortID": 5,
        "Profit": 44,
        "Route": [
          {
            "StartTime": 243,
            "SelectedDay": 2,
            "ID": "PE-FWI-4-1011"
          },
          {
            "StartTime": 1092,
            "SelectedDay": 2,
            "ID": "PE-FWI-4-6721"
          },
          {
            "StartTime": 2043,
            "SelectedDay": 2,
            "ID": "PE-FWI-4-9238"
          },
          {
            "StartTime": 3006,
            "SelectedDay": 2,
            "ID": "PE-FWI-4-5049"
          },
          {
            "StartTime": 4433,
            "SelectedDay": 2,
            "ID": "PE-FWI-4-4965"
          },
          {
            "StartTime": 5400,
            "SelectedDay": 2,
            "ID": "PE-FWI-4-1935"
          },
          {
            "StartTime": 6085,
            "SelectedDay": 2,
            "ID": "PE-FWI-4-7662"
          },
          {
            "StartTime": 7071,
            "SelectedDay": 2,
            "ID": "PE-FWI-4-4307"
          },
          {
            "StartTime": 7815,
            "SelectedDay": 2,
            "ID": "PE-FWI-4-5348"
          },
          {
            "StartTime": 9000,
            "SelectedDay": 2,
            "ID": "MT-FWI-13"
          },
          {
            "StartTime": 16224,
            "SelectedDay": 2,
            "ID": "PE-FWI-1-2811"
          },
          {
            "StartTime": 17464,
            "SelectedDay": 2,
            "ID": "PE-FWI-2-5751"
          },
          {
            "StartTime": 18151,
            "SelectedDay": 2,
            "ID": "PE-FWI-4-903"
          },
          {
            "StartTime": 18825,
            "SelectedDay": 2,
            "ID": "PE-FWI-4-735"
          },
          {
            "StartTime": 19727,
            "SelectedDay": 2,
            "ID": "PE-FWI-4-2745"
          },
          {
            "StartTime": 20697,
            "SelectedDay": 2,
            "ID": "PE-FWI-4-7434"
          }
        ]
      },
      {
        "CohortID": 6,
        "Profit": 55,
        "Route": [
          {
            "StartTime": 146,
            "SelectedDay": 2,
            "ID": "PE-FWI-3-3769"
          },
          {
            "StartTime": 902,
            "SelectedDay": 2,
            "ID": "PE-FWI-1-6555"
          },
          {
            "StartTime": 1638,
            "SelectedDay": 2,
            "ID": "PE-FWI-4-4774"
          },
          {
            "StartTime": 2428,
            "SelectedDay": 2,
            "ID": "PE-FWI-4-7812"
          },
          {
            "StartTime": 3171,
            "SelectedDay": 2,
            "ID": "PE-FWI-4-3584"
          },
          {
            "StartTime": 3951,
            "SelectedDay": 2,
            "ID": "PE-FWI-4-101"
          },
          {
            "StartTime": 4690,
            "SelectedDay": 2,
            "ID": "PE-FWI-4-4983"
          },
          {
            "StartTime": 5573,
            "SelectedDay": 2,
            "ID": "PE-FWI-4-5071"
          },
          {
            "StartTime": 6469,
            "SelectedDay": 2,
            "ID": "PE-FWI-4-3578"
          },
          {
            "StartTime": 7200,
            "SelectedDay": 2,
            "ID": "MT-FWI-14"
          },
          {
            "StartTime": 12942,
            "SelectedDay": 2,
            "ID": "PE-FWI-4-5952"
          },
          {
            "StartTime": 13811,
            "SelectedDay": 2,
            "ID": "PE-FWI-4-3310"
          },
          {
            "StartTime": 14796,
            "SelectedDay": 2,
            "ID": "PE-FWI-4-4872"
          },
          {
            "StartTime": 15700,
            "SelectedDay": 2,
            "ID": "PE-FWI-4-2832"
          },
          {
            "StartTime": 16364,
            "SelectedDay": 2,
            "ID": "PE-FWI-4-3313"
          },
          {
            "StartTime": 17285,
            "SelectedDay": 2,
            "ID": "PE-FWI-4-8852"
          },
          {
            "StartTime": 18160,
            "SelectedDay": 2,
            "ID": "PE-FWI-4-907"
          },
          {
            "StartTime": 18770,
            "SelectedDay": 2,
            "ID": "PE-FWI-4-8374"
          },
          {
            "StartTime": 19596,
            "SelectedDay": 2,
            "ID": "PE-FWI-4-5691"
          },
          {
            "StartTime": 20461,
            "SelectedDay": 2,
            "ID": "PE-FWI-4-5567"
          }
        ]
      }
    ]
  }
}